odoo9_addon_sale_order_line_sequence-9.0.1.0.0.99.dev6-py3.6-nspkg.pth
odoo_addons/sale_order_line_sequence/README.rst
odoo_addons/sale_order_line_sequence/__init__.py
odoo_addons/sale_order_line_sequence/__openerp__.py
odoo_addons/sale_order_line_sequence/i18n/ca.po
odoo_addons/sale_order_line_sequence/i18n/es.po
odoo_addons/sale_order_line_sequence/i18n/sale_order_line_sequence.pot
odoo_addons/sale_order_line_sequence/model/__init__.py
odoo_addons/sale_order_line_sequence/model/sale_order.py
odoo_addons/sale_order_line_sequence/static/description/icon.png
odoo_addons/sale_order_line_sequence/views/sale_view.xml
odoo9_addon_sale_order_line_sequence-9.0.1.0.0.99.dev6.dist-info/METADATA
odoo9_addon_sale_order_line_sequence-9.0.1.0.0.99.dev6.dist-info/WHEEL
odoo9_addon_sale_order_line_sequence-9.0.1.0.0.99.dev6.dist-info/namespace_packages.txt
odoo9_addon_sale_order_line_sequence-9.0.1.0.0.99.dev6.dist-info/top_level.txt
odoo9_addon_sale_order_line_sequence-9.0.1.0.0.99.dev6.dist-info/RECORD
