Metadata-Version: 2.1
Name: odoo9-addon-sale-order-line-sequence
Version: 9.0.1.0.0.99.dev6
Summary: Propagates SO line sequence to invoices and stock picking.
Home-page: https://www.eficent.com/
Author: Eficent, Serpent CS, Odoo Community Association (OCA)
Author-email: support@odoo-community.org
License: AGPL-3
Platform: UNKNOWN
Classifier: Programming Language :: Python
Classifier: Framework :: Odoo
Classifier: License :: OSI Approved :: GNU Affero General Public License v3
Requires-Python: ~=2.7
Requires-Dist: odoo (<9.1a,>=9.0a)
